zc_madlibs/__init__.py
zc_madlibs/cli.py
zc_madlibs/codemas.json
zc_madlibs/nightout.json
zc_madlibs-0.1.1.dist-info/METADATA
zc_madlibs-0.1.1.dist-info/WHEEL
zc_madlibs-0.1.1.dist-info/entry_points.txt
zc_madlibs-0.1.1.dist-info/RECORD
