Metadata-Version: 2.4
Name: zc-madlibs
Version: 0.1.1
Summary: 
Author: Claire Acton
Author-email: 22026811@saultcollege.ca
Requires-Python: >=3.9
Classifier: Programming Language :: Python :: 3
Classifier: Programming Language :: Python :: 3.9
Classifier: Programming Language :: Python :: 3.10
Classifier: Programming Language :: Python :: 3.11
Classifier: Programming Language :: Python :: 3.12
Classifier: Programming Language :: Python :: 3.13
Classifier: Programming Language :: Python :: 3.14
Requires-Dist: regex (>=2025.11.3,<2026.0.0)
Requires-Dist: requests (>=2.32.5,<3.0.0)
